README.md
setup.py
latent_space_visualizer/__init__.py
latent_space_viz.egg-info/PKG-INFO
latent_space_viz.egg-info/SOURCES.txt
latent_space_viz.egg-info/dependency_links.txt
latent_space_viz.egg-info/requires.txt
latent_space_viz.egg-info/top_level.txt